atorch/__init__.py
atorch/amp/__init__.py
atorch/amp/amp.py
atorch/amp/hook.py
atorch/amp/pipe_amp.py
atorch/auto/__init__.py
atorch/auto/accelerate.py
atorch/auto/auto_accelerate_context.py
atorch/auto/clip_grad_norm.py
atorch/auto/device_context.py
atorch/auto/engine_client.py
atorch/auto/model_context.py
atorch/auto/strategy.py
atorch/auto/task.py
atorch/auto/analyser/__init__.py
atorch/auto/analyser/analyser.py
atorch/auto/dry_runner/__init__.py
atorch/auto/dry_runner/dry_runner.py
atorch/auto/engine/__init__.py
atorch/auto/engine/acceleration_engine.py
atorch/auto/engine/analyser_result.py
atorch/auto/engine/client.py
atorch/auto/engine/executor.py
atorch/auto/engine/optimization_method.py
atorch/auto/engine/planner.py
atorch/auto/engine/servicer.py
atorch/auto/engine/strategy.py
atorch/auto/engine/task.py
atorch/auto/engine/sg_algo/__init__.py
atorch/auto/engine/sg_algo/bayes_opt_sg.py
atorch/auto/engine/sg_algo/combination_sg.py
atorch/auto/engine/sg_algo/sg_algo_lib.py
atorch/auto/engine/sg_algo/sg_algorithm.py
atorch/auto/engine/sg_algo/utils.py
atorch/auto/engine/sg_algo/hebo/__init__.py
atorch/auto/engine/sg_algo/hebo/acq_optimizers/__init__.py
atorch/auto/engine/sg_algo/hebo/acq_optimizers/evolution_optimizer.py
atorch/auto/engine/sg_algo/hebo/acquisitions/__init__.py
atorch/auto/engine/sg_algo/hebo/acquisitions/acq.py
atorch/auto/engine/sg_algo/hebo/design_space/__init__.py
atorch/auto/engine/sg_algo/hebo/design_space/categorical_param.py
atorch/auto/engine/sg_algo/hebo/design_space/design_space.py
atorch/auto/engine/sg_algo/hebo/design_space/param.py
atorch/auto/engine/sg_algo/hebo/models/__init__.py
atorch/auto/engine/sg_algo/hebo/models/base_model.py
atorch/auto/engine/sg_algo/hebo/models/layers.py
atorch/auto/engine/sg_algo/hebo/models/model_factory.py
atorch/auto/engine/sg_algo/hebo/models/util.py
atorch/auto/engine/sg_algo/hebo/models/gauss_process/__init__.py
atorch/auto/engine/sg_algo/hebo/models/gauss_process/gpy_wgp.py
atorch-0.2.5.dist-info/LICENSE
atorch-0.2.5.dist-info/METADATA
atorch-0.2.5.dist-info/WHEEL
atorch-0.2.5.dist-info/top_level.txt
atorch-0.2.5.dist-info/RECORD
